azure_fhir_mcp_server/__init__.py
azure_fhir_mcp_server/server.py
azure_fhir_mcp_server/config/catalog.yaml
azure_fhir_mcp_server-1.2.0.dist-info/METADATA
azure_fhir_mcp_server-1.2.0.dist-info/WHEEL
azure_fhir_mcp_server-1.2.0.dist-info/entry_points.txt
azure_fhir_mcp_server-1.2.0.dist-info/licenses/LICENSE
azure_fhir_mcp_server-1.2.0.dist-info/RECORD
