Metadata-Version: 2.4
Name: azure-fhir-mcp-server
Version: 1.2.0
Summary: Azure AHDS FHIR MCP Server
Project-URL: Homepage, https://github.com/erikhoward/azure-fhir-mcp-server
Project-URL: Bug Tracker, https://github.com/erikhoward/azure-fhir-mcp-server/issues
Project-URL: Documentation, https://github.com/erikhoward/azure-fhir-mcp-server/tree/main#azure-fhir-mcp-server-
Author-email: Erik Howard <erikhoward@pm.me>
License: MIT
License-File: LICENSE
Keywords: ahds,azure,fhir,healthcare,llm,mcp,model-context-protocol
Classifier: Development Status :: 4 - Beta
Classifier: Intended Audience :: Developers
Classifier: License :: OSI Approved :: MIT License
Classifier: Operating System :: OS Independent
Classifier: Programming Language :: Python :: 3
Classifier: Programming Language :: Python :: 3.13
Requires-Python: >=3.13
Requires-Dist: fastmcp>=2.12.4
Requires-Dist: msal>=1.28.0
Requires-Dist: python-dotenv>=1.1.0
Requires-Dist: pyyaml>=6.0
Requires-Dist: requests>=2.32.3
Requires-Dist: uvicorn[standard]>=0.37.0
Provides-Extra: dev
Requires-Dist: pytest-asyncio>=0.24.0; extra == 'dev'
Requires-Dist: pytest-cov>=5.0.0; extra == 'dev'
Requires-Dist: pytest>=8.0.0; extra == 'dev'
